frozendate.py
frozendate-0.1.4.dist-info/LICENSE.txt
frozendate-0.1.4.dist-info/METADATA
frozendate-0.1.4.dist-info/WHEEL
frozendate-0.1.4.dist-info/top_level.txt
frozendate-0.1.4.dist-info/RECORD
