Metadata-Version: 2.1
Name: frozendate
Version: 0.1.4
Summary: Frozen date: freeze datetime.now at a known value for testing
Home-page: https://bitbucket.org/ollyc/frozendate/
Author: Oliver Cope
Author-email: oliver@redgecko.org
License: BSD
Platform: UNKNOWN
Classifier: License :: OSI Approved :: BSD License
Classifier: Topic :: Software Development :: Testing
Classifier: Programming Language :: Python :: 2.7
Classifier: Programming Language :: Python :: 3.6
Classifier: Programming Language :: Python :: 3.7
License-File: LICENSE.txt
Requires-Dist: mock
